{
  "type": "boolean",
  "title": {
    "en": "Heat alarm",
    "nl": "Hittealarm"
  },
  "desc": {
    "en": "True when extreme heat has been detected",
    "nl": "Gaat af als er extreme hitte gedetecteerd wordt"
  },
  "insights": true,
  "insightsTitleTrue": {
    "en": "Heat alarm turned on",
    "nl": "Hittealarm ging af"
  },
  "insightsTitleFalse": {
    "en": "Heat alarm turned off",
    "nl": "Hittealarm ging uit"
  },
  "getable": true,
  "setable": false,
  "uiComponent": "sensor",
  "$flow": {
    "triggers": [
      {
        "id": "alarm_heat_true",
        "title": {
          "en": "The heat alarm turned on",
          "nl": "Het hitte alarm gaat aan"
        }
      },
      {
        "id": "alarm_heat_false",
        "title": {
          "en": "The heat alarm turned off",
          "nl": "Het hitte alarm gaat uit"
        }
      }
    ],
    "conditions": [
      {
        "id": "alarm_heat",
        "title": {
          "en": "The heat alarm is !{{on|off}}",
          "nl": "Het hitte alarm is !{{aan|uit}}"
        }
      }
    ]
  }
}