{
  "type": "number",
  "title": {
    "en": "Energy Storage",
    "nl": "Energieopslag"
  },
  "units": {
    "en": "Wh"
  },
  "desc": {
    "en": "The energy storage in watt-hours."
  },
  "insights": true,
  "chartType": "spline",
  "decimals": 2,
  "getable": true,
  "setable": false,
  "uiComponent": "sensor",
  "$flow": {
    "triggers": [
      {
        "id": "measure_energy_storage_changed",
        "title": {
          "en": "The energy storage changed"
        },
        "tokens": [
          {
            "name": "$id",
            "title": "$title",
            "type": "$type",
            "example": 2
          }
        ]
      }
    ]
  }
}